httpolice/__init__.py
httpolice/__metadata__.py
httpolice/blackboard.py
httpolice/citation.py
httpolice/cli.py
httpolice/codings.py
httpolice/exchange.py
httpolice/framing1.py
httpolice/header.py
httpolice/helpers.py
httpolice/message.py
httpolice/notice.py
httpolice/notices.xml
httpolice/parse.py
httpolice/request.py
httpolice/response.py
httpolice/stream.py
httpolice/structure.py
httpolice/inputs/__init__.py
httpolice/inputs/common.py
httpolice/inputs/har.py
httpolice/inputs/streams.py
httpolice/known/__init__.py
httpolice/known/alt_svc_param.csv
httpolice/known/auth_scheme.csv
httpolice/known/cache_directive.csv
httpolice/known/content_coding.csv
httpolice/known/forwarded_param.csv
httpolice/known/header.csv
httpolice/known/hsts_directive.csv
httpolice/known/media_type.csv
httpolice/known/method.csv
httpolice/known/preference.csv
httpolice/known/product.csv
httpolice/known/range_unit.csv
httpolice/known/status_code.csv
httpolice/known/transfer_coding.csv
httpolice/known/upgrade_token.csv
httpolice/known/warn_code.csv
httpolice/reports/__init__.py
httpolice/reports/common.py
httpolice/reports/html.css
httpolice/reports/html.js
httpolice/reports/html.py
httpolice/reports/text.py
httpolice/syntax/__init__.py
httpolice/syntax/common.py
httpolice/syntax/internal.py
httpolice/syntax/rfc2616.py
httpolice/syntax/rfc3986.py
httpolice/syntax/rfc4647.py
httpolice/syntax/rfc5646.py
httpolice/syntax/rfc5789.py
httpolice/syntax/rfc6266.py
httpolice/syntax/rfc6749.py
httpolice/syntax/rfc6797.py
httpolice/syntax/rfc6838.py
httpolice/syntax/rfc7230.py
httpolice/syntax/rfc7231.py
httpolice/syntax/rfc7232.py
httpolice/syntax/rfc7233.py
httpolice/syntax/rfc7234.py
httpolice/syntax/rfc7235.py
httpolice/syntax/rfc7239.py
httpolice/syntax/rfc7240.py
httpolice/syntax/rfc7540.py
httpolice/syntax/rfc7838.py
httpolice/syntax/rfc8187.py
httpolice/syntax/rfc8288.py
httpolice/syntax/w3c_ldp.py
httpolice/syntax/whatwg_fetch.py
httpolice/util/__init__.py
httpolice/util/data.py
HTTPolice-0.9.0.dist-info/LICENSE.txt
HTTPolice-0.9.0.dist-info/METADATA
HTTPolice-0.9.0.dist-info/WHEEL
HTTPolice-0.9.0.dist-info/entry_points.txt
HTTPolice-0.9.0.dist-info/top_level.txt
HTTPolice-0.9.0.dist-info/RECORD
