Metadata-Version: 2.1
Name: HTTPolice
Version: 0.9.0
Summary: Validator for HTTP
Home-page: https://github.com/vfaronov/httpolice
Author: Vasiliy Faronov
Author-email: vfaronov@gmail.com
License: MIT
Keywords: HTTP message request response standards RFC lint validator
Platform: UNKNOWN
Classifier: Intended Audience :: Developers
Classifier: License :: OSI Approved :: MIT License
Classifier: Programming Language :: Python :: 3
Classifier: Programming Language :: Python :: 3 :: Only
Classifier: Programming Language :: Python :: 3.4
Classifier: Programming Language :: Python :: 3.5
Classifier: Programming Language :: Python :: 3.6
Classifier: Programming Language :: Python :: 3.7
Classifier: Programming Language :: Python :: Implementation :: CPython
Classifier: Programming Language :: Python :: Implementation :: PyPy
Classifier: Topic :: Internet :: WWW/HTTP
Classifier: Topic :: Software Development :: Quality Assurance
Requires-Python: >= 3.4
Requires-Dist: lxml (>=4.1.0)
Requires-Dist: bitstring (>=3.1.4)
Requires-Dist: dominate (>=2.2.0)
Requires-Dist: defusedxml (>=0.5.0)
Requires-Dist: Brotli (>=1.0.1)
